waldur_site_agent_mup/__init__.py
waldur_site_agent_mup/backend.py
waldur_site_agent_mup/client.py
waldur_site_agent_mup-0.8.2.dist-info/METADATA
waldur_site_agent_mup-0.8.2.dist-info/WHEEL
waldur_site_agent_mup-0.8.2.dist-info/entry_points.txt
waldur_site_agent_mup-0.8.2.dist-info/RECORD
