Metadata-Version: 2.4
Name: waldur-site-agent-mup
Version: 0.8.2
Summary: MUP plugin for Waldur Site Agent
Author-email: OpenNode Team <info@opennodecloud.com>
Requires-Python: <4,>=3.9
Requires-Dist: waldur-site-agent>=0.7.0
